{
  "additional_prohibitions": null,
  "category": "Economics",
  "contract_terms_url": "https://kalshi-public-docs.s3.amazonaws.com/contract_terms/OIL.pdf",
  "contract_url": "https://kalshi-public-docs.s3.us-east-1.amazonaws.com/regulatory/product-certifications/OIL.pdf",
  "fee_multiplier": 1,
  "fee_type": "quadratic",
  "frequency": "monthly",
  "settlement_sources": [
    {
      "name": "Energy Information Administration",
      "url": "https://www.eia.gov/dnav/pet/PET_PRI_SPT_S1_D.htm"
    }
  ],
  "tags": [
    "Oil and energy"
  ],
  "ticker": "KXOIL",
  "title": "Price of oil monthly"
}